mass/__init__.py
mass/exceptions.py
mass/core/__init__.py
mass/core/mass_configuration.py
mass/core/mass_metabolite.py
mass/core/mass_model.py
mass/core/mass_reaction.py
mass/core/mass_solution.py
mass/core/units.py
mass/enzyme_modules/__init__.py
mass/enzyme_modules/enzyme_module.py
mass/enzyme_modules/enzyme_module_dict.py
mass/enzyme_modules/enzyme_module_form.py
mass/enzyme_modules/enzyme_module_reaction.py
mass/example_data/__init__.py
mass/example_data/maps/RBC.glycolysis.map.json
mass/example_data/maps/multicompartment_map.json
mass/example_data/maps/phosphate_trafficking_map.json
mass/example_data/maps/sb2_RBC_map.json
mass/example_data/maps/sb2_amp_salvage_network_map.json
mass/example_data/maps/sb2_glycolysis_map.json
mass/example_data/maps/sb2_pentose_phosphate_pathway_map.json
mass/example_data/maps/simple_toy_map.json
mass/example_data/models/Glycolysis.json
mass/example_data/models/Glycolysis_FKRM.json
mass/example_data/models/Glycolysis_Hb_HEX1.json
mass/example_data/models/Glycolysis_Hb_PFK.json
mass/example_data/models/Glycolysis_Hb_PYK.json
mass/example_data/models/Hemoglobin.json
mass/example_data/models/Model_to_Repair.json
mass/example_data/models/MultiCompartment.json
mass/example_data/models/Phosphate_Trafficking.json
mass/example_data/models/SB2_AMPSalvageNetwork.json
mass/example_data/models/SB2_Glycolysis.json
mass/example_data/models/SB2_Hemoglobin.json
mass/example_data/models/SB2_PFK.json
mass/example_data/models/SB2_PentosePhosphatePathway.json
mass/example_data/models/Simple_Toy.json
mass/example_data/models/Simple_Toy.xml
mass/example_data/models/WholeCellRBC_MA_Rates.json
mass/example_data/models/WholeCellRBC_MA_Rates.xml
mass/example_data/models/WholeCellRBC_MM_Rates.json
mass/example_data/models/WholeCellRBC_MM_Rates.xml
mass/example_data/models/textbook.json
mass/example_data/models/textbook.xml
mass/io/__init__.py
mass/io/dict.py
mass/io/json.py
mass/io/sbml.py
mass/simulation/__init__.py
mass/simulation/ensemble.py
masspy-0.1.7.dist-info/LICENSE
masspy-0.1.7.dist-info/METADATA
masspy-0.1.7.dist-info/WHEEL
masspy-0.1.7.dist-info/top_level.txt
masspy-0.1.7.dist-info/zip-safe
masspy-0.1.7.dist-info/RECORD
